shipzo_cmd/__init__.py
shipzo_cmd/cmd.py
shipzo_cmd/shipzo_cmd.py
shipzo_cmd-0.3.1.dist-info/METADATA
shipzo_cmd-0.3.1.dist-info/WHEEL
shipzo_cmd-0.3.1.dist-info/top_level.txt
shipzo_cmd-0.3.1.dist-info/RECORD
