Metadata-Version: 2.4
Name: shipzo_cmd
Version: 0.3.1
Summary: 통합 project package
Author-email: hun0219 <gsw98000@gmail.com>
License: MIT
Project-URL: GitHub, https://github.com/hun0219/shipzo_cmd
Project-URL: Homepage, https://github.com/hun0219/shipzo_cmd
Project-URL: Issues, https://github.com/hun0219/shipzo_cmd/Issues
Requires-Python: >=3.9
Requires-Dist: shipzo-plus-hun>=0.1.6
Requires-Dist: shipzo-mult-hun>=0.1.0
Requires-Dist: shipzo-divide-hun>=0.1.0
